accelerometer/__init__.py
accelerometer/_version.py
accelerometer/accCollateSummary.py
accelerometer/accPlot.py
accelerometer/accProcess.py
accelerometer/accWriteCmds.py
accelerometer/circadian.py
accelerometer/classification.py
accelerometer/device.py
accelerometer/models.py
accelerometer/summarisation.py
accelerometer/utils.py
accelerometer/activityModels/README.md
accelerometer/java/AccStats.class
accelerometer/java/AccStats.java
accelerometer/java/AccelerometerParser.class
accelerometer/java/AccelerometerParser.java
accelerometer/java/ActigraphReader.class
accelerometer/java/ActigraphReader.java
accelerometer/java/AxivityReader.class
accelerometer/java/AxivityReader.java
accelerometer/java/BandpassFilter.class
accelerometer/java/BandpassFilter.java
accelerometer/java/CsvReader.class
accelerometer/java/CsvReader.java
accelerometer/java/DeviceReader.class
accelerometer/java/DeviceReader.java
accelerometer/java/EpochWriter.class
accelerometer/java/EpochWriter.java
accelerometer/java/Features.class
accelerometer/java/Features.java
accelerometer/java/Filter.class
accelerometer/java/Filter.java
accelerometer/java/GENEActivReader.class
accelerometer/java/GENEActivReader.java
accelerometer/java/JTransforms-3.1-with-dependencies.jar
accelerometer/java/LowpassFilter.class
accelerometer/java/LowpassFilter.java
accelerometer/java/NpyWriter.class
accelerometer/java/NpyWriter.java
accelerometer/java/README.md
accelerometer/java/Resample.class
accelerometer/java/Resample.java
accelerometer/java/logging.properties
accelerometer-7.5.0.dist-info/licenses/LICENSE.md
accelerometer-7.5.0.dist-info/METADATA
accelerometer-7.5.0.dist-info/WHEEL
accelerometer-7.5.0.dist-info/entry_points.txt
accelerometer-7.5.0.dist-info/top_level.txt
accelerometer-7.5.0.dist-info/RECORD
