Metadata-Version: 2.4
Name: accelerometer
Version: 7.5.0
Summary: A package to extract meaningful health information from large accelerometer datasets e.g. how much time individuals spend in sleep, sedentary behaviour, walking and moderate intensity physical activity
Home-page: https://github.com/activityMonitoring/biobankAccelerometerAnalysis
Download-URL: https://github.com/activityMonitoring/biobankAccelerometerAnalysis
Author: Aiden Doherty, Shing Chan, Rosemary Walmsley, Hang Yuan
Maintainer: Shing Chan
Maintainer-email: shing.chan@ndph.ox.ac.uk
License: See LICENSE.md
Keywords: wearables,accelerometer,health data science,human activity recognition
Classifier: Programming Language :: Python :: 3
Classifier: Topic :: Scientific/Engineering
Classifier: Topic :: Scientific/Engineering :: Bio-Informatics
Classifier: Topic :: Scientific/Engineering :: Information Analysis
Classifier: Topic :: Scientific/Engineering :: Medical Science Apps.
Requires-Python: >=3.7, <3.11
License-File: LICENSE.md
Requires-Dist: numpy==1.21.*
Requires-Dist: scipy==1.7.*
Requires-Dist: matplotlib==3.5.*
Requires-Dist: pandas==1.3.*
Requires-Dist: tqdm==4.65.*
Requires-Dist: statsmodels==0.13.*
Requires-Dist: joblib==1.1.*
Requires-Dist: imbalanced-learn==0.8.1
Requires-Dist: scikit-learn==1.0.2
Provides-Extra: dev
Requires-Dist: flake8; extra == "dev"
Requires-Dist: autopep8; extra == "dev"
Requires-Dist: ipython; extra == "dev"
Requires-Dist: ipdb; extra == "dev"
Requires-Dist: twine; extra == "dev"
Requires-Dist: tomli; extra == "dev"
Provides-Extra: docs
Requires-Dist: sphinx>=4.2; extra == "docs"
Requires-Dist: sphinx_rtd_theme>=1.0; extra == "docs"
Requires-Dist: readthedocs-sphinx-search>=0.1; extra == "docs"
Requires-Dist: sphinxcontrib-programoutput>=0.17; extra == "docs"
Requires-Dist: docutils<0.18; extra == "docs"
Dynamic: author
Dynamic: classifier
Dynamic: description
Dynamic: description-content-type
Dynamic: download-url
Dynamic: home-page
Dynamic: keywords
Dynamic: license
Dynamic: license-file
Dynamic: maintainer
Dynamic: maintainer-email
Dynamic: provides-extra
Dynamic: requires-dist
Dynamic: requires-python
Dynamic: summary
